hello_cli/__init__.py
hello_cli/cli.py
hello_cli/hello_web_client.py
hello_cli_lightlord-0.1.2.dist-info/METADATA
hello_cli_lightlord-0.1.2.dist-info/WHEEL
hello_cli_lightlord-0.1.2.dist-info/entry_points.txt
hello_cli_lightlord-0.1.2.dist-info/top_level.txt
hello_cli_lightlord-0.1.2.dist-info/RECORD
