Metadata-Version: 2.4
Name: hello_cli_lightlord
Version: 0.1.2
Summary: 示例包
Author-email: Light Lord <37751149@qq.com>
License-Expression: MIT
Project-URL: Homepage, https://github.com/you/my_pkg
Requires-Python: >=3.11
Requires-Dist: gradio<6,>=5.44.0
